README.md
setup.py
celare/__init__.py
celare/celare.py
celare/gitignore.py
celare/read.py
celare.egg-info/PKG-INFO
celare.egg-info/SOURCES.txt
celare.egg-info/dependency_links.txt
celare.egg-info/top_level.txt