Metadata-Version: 2.1
Name: celare
Version: 0.0.2
Summary: Package to write and hide tokens, passwords, secret keys, without having to put them in the code
Home-page: https://github.com/MariaEduardaDeAzevedo/celare
Author: Maria Eduarda de Azevedo
Author-email: maria.silva@ccc.ufcg.edu.br
License: MIT License
Keywords: token,hidden,api,keys
Platform: UNKNOWN
